htmlfy/__init__.py
htmlfy/minifier.py
htmlfy-0.1.3.dist-info/LICENSE
htmlfy-0.1.3.dist-info/METADATA
htmlfy-0.1.3.dist-info/WHEEL
htmlfy-0.1.3.dist-info/top_level.txt
htmlfy-0.1.3.dist-info/RECORD
