Metadata-Version: 2.1
Name: htmlfy
Version: 0.1.3
Summary: Python package for HTML minification
Home-page: https://github.com/AlexxNB/htmlfy
Author: Alexey Schebelev
License: UNKNOWN
Platform: UNKNOWN
Classifier: Programming Language :: Python :: 3
Classifier: License :: OSI Approved :: BSD License
Classifier: Operating System :: OS Independent
